iqs_api/__init__.py
iqs_api/api_decorator.py
iqs_api/iqs_authentication.py
iqs_api/iqs_connection.py
iqs_client/__init__.py
iqs_client/api_client.py
iqs_client/configuration.py
iqs_client/exceptions.py
iqs_client/rest.py
iqs_client/api/__init__.py
iqs_client/api/acquisition_api.py
iqs_client/api/analysis_api.py
iqs_client/api/async_api.py
iqs_client/api/demo_api.py
iqs_client/api/deprecated_api.py
iqs_client/api/impact_analysis_api.py
iqs_client/api/in_memory_index_api.py
iqs_client/api/integration_api.py
iqs_client/api/mms_repository_api.py
iqs_client/api/persistent_index_api.py
iqs_client/api/queries_api.py
iqs_client/api/query_execution_api.py
iqs_client/api/repository_api.py
iqs_client/api/server_management_api.py
iqs_client/api/validation_api.py
iqs_client/models/__init__.py
iqs_client/models/acquisition_options.py
iqs_client/models/analysis_configuration.py
iqs_client/models/analysis_configuration_details.py
iqs_client/models/analysis_configuration_identifier.py
iqs_client/models/analysis_configuration_list.py
iqs_client/models/analysis_execution_request.py
iqs_client/models/analysis_result.py
iqs_client/models/analysis_results.py
iqs_client/models/analysis_rule.py
iqs_client/models/analysis_rule_details.py
iqs_client/models/analysis_rule_result.py
iqs_client/models/analysis_rule_result_match.py
iqs_client/models/analysis_user_error_response.py
iqs_client/models/argument.py
iqs_client/models/async_index_message.py
iqs_client/models/attribute_slot.py
iqs_client/models/attribute_store_entry.py
iqs_client/models/branch.py
iqs_client/models/branch_with_dependent_elements.py
iqs_client/models/close_acquisition_request.py
iqs_client/models/close_acquisition_response.py
iqs_client/models/compartment_link.py
iqs_client/models/compartment_link_request.py
iqs_client/models/compartment_link_response.py
iqs_client/models/compartment_operation_progress.py
iqs_client/models/compartment_operation_state.py
iqs_client/models/compartment_operation_state_details.py
incqueryserver_api_python_client-0.27.0.dist-info/METADATA
incqueryserver_api_python_client-0.27.0.dist-info/WHEEL
incqueryserver_api_python_client-0.27.0.dist-info/top_level.txt
incqueryserver_api_python_client-0.27.0.dist-info/RECORD
