Metadata-Version: 2.1
Name: incqueryserver-api-python-client
Version: 0.27.0
Summary: IncQuery Server Web API
Home-page: https://incquery.io
Author: IncQueryLabs
Author-email: info@incquerylabs.com
License: UNKNOWN
Keywords: OpenAPI,OpenAPI-Generator,IncQuery Server Web API
Platform: UNKNOWN
Requires-Dist: urllib3 (>=1.15)
Requires-Dist: six (>=1.10)
Requires-Dist: certifi
Requires-Dist: python-dateutil
